pmo/__init__.py
pmo/cli.py
pmo/logs.py
pmo/service.py
pmo/util.py
pmo-0.5.2.dist-info/licenses/LICENSE
pmo-0.5.2.dist-info/METADATA
pmo-0.5.2.dist-info/WHEEL
pmo-0.5.2.dist-info/entry_points.txt
pmo-0.5.2.dist-info/top_level.txt
pmo-0.5.2.dist-info/RECORD
