Metadata-Version: 2.4
Name: pmo
Version: 0.5.2
Summary: simple process manager
Author-email: simpxx <simpxx@gmail.com>
License: MIT
Keywords: command-line,tool
Classifier: Programming Language :: Python :: 3
Classifier: License :: OSI Approved :: MIT License
Classifier: Operating System :: OS Independent
Requires-Python: >=3.10
License-File: LICENSE
Requires-Dist: freezegun>=1.5.1
Requires-Dist: psutil>=7.0.0
Requires-Dist: nvidia-ml-py>=12.0.0
Requires-Dist: python-dotenv>=1.1.0
Requires-Dist: pyyaml>=6.0.2
Requires-Dist: rich>=14.0.0
Dynamic: license-file
